agentvault_server_sdk/__init__.py
agentvault_server_sdk/agent.py
agentvault_server_sdk/exceptions.py
agentvault_server_sdk/fastapi_integration.py
agentvault_server_sdk/mcp_utils.py
agentvault_server_sdk/packager/__init__.py
agentvault_server_sdk/packager/cli.py
agentvault_server_sdk/state.py
agentvault_server_sdk-0.1.1.dist-info/entry_points.txt
agentvault_server_sdk-0.1.1.dist-info/LICENSE
agentvault_server_sdk-0.1.1.dist-info/METADATA
agentvault_server_sdk-0.1.1.dist-info/WHEEL
agentvault_server_sdk-0.1.1.dist-info/RECORD
