Metadata-Version: 2.3
Name: agentvault-server-sdk
Version: 0.1.1
Summary: Server SDK for building AgentVault A2A compliant agents.
License: Apache-2.0
Author: Raphael Zbigniew Jeziorny
Author-email: AgentVault@proton.me
Requires-Python: >=3.10,<3.12
Classifier: License :: OSI Approved :: Apache Software License
Classifier: Programming Language :: Python :: 3
Classifier: Programming Language :: Python :: 3.10
Classifier: Programming Language :: Python :: 3.11
Provides-Extra: dev
Requires-Dist: agentvault (>=0.2.0,<0.3.0)
Requires-Dist: fastapi (>=0.111,<0.112)
Requires-Dist: freezegun (>=1.1.0) ; extra == "dev"
Requires-Dist: pytest (>=7.0,<9.0) ; extra == "dev"
Requires-Dist: pytest-asyncio (>=0.23,<0.24) ; extra == "dev"
Requires-Dist: typer (>=0.9.0)
